aflr/__init__.py
aflr/api_request.py
aflr/helper_classes.py
aflr/api_resources/__init__.py
aflr/api_resources/file.py
aflr/api_resources/mastering.py
aflr/api_resources/script.py
aflr/api_resources/sound.py
aflr/api_resources/speech.py
aflr/api_resources/voice.py
tests/__init__.py
tests/test_config.py
aflr-0.8.1.dist-info/LICENSE
aflr-0.8.1.dist-info/METADATA
aflr-0.8.1.dist-info/WHEEL
aflr-0.8.1.dist-info/top_level.txt
aflr-0.8.1.dist-info/RECORD
