Metadata-Version: 2.1
Name: aflr
Version: 0.8.1
Summary: Python library for the Aflorithmic api.audio API
Home-page: https://github.com/aflorithmic/aflr_python
Author: Antonio Tripiana
Author-email: antonio@aflorithmic.ai
License: UNKNOWN
Platform: UNKNOWN
Classifier: Programming Language :: Python :: 3
Classifier: License :: OSI Approved :: MIT License
Classifier: Operating System :: OS Independent
Requires-Python: >=3.6
Requires-Dist: requests (>=2.20) ; python_version >= "3.0"
